dtp/.gitignore
dtp/__init__.py
dtp/config.py
dtp/constants.py
dtp/settings.toml
dtp/application/__init__.py
dtp/application/instance.py
dtp/application/lifespan.py
fastapi_dtp-0.1.0.dist-info/METADATA
fastapi_dtp-0.1.0.dist-info/WHEEL
fastapi_dtp-0.1.0.dist-info/entry_points.txt
fastapi_dtp-0.1.0.dist-info/RECORD
